mothrpy/__init__.py
mothrpy/client.py
mothrpy/request.py
mothrpy/schema.graphql
mothrpy-0.3.0.dist-info/LICENSE
mothrpy-0.3.0.dist-info/METADATA
mothrpy-0.3.0.dist-info/WHEEL
mothrpy-0.3.0.dist-info/top_level.txt
mothrpy-0.3.0.dist-info/RECORD
